sass_processor/__init__.py
sass_processor/apps.py
sass_processor/finders.py
sass_processor/processor.py
sass_processor/storage.py
sass_processor/types.py
sass_processor/utils.py
sass_processor/jinja2/__init__.py
sass_processor/jinja2/ext.py
sass_processor/management/__init__.py
sass_processor/management/commands/__init__.py
sass_processor/management/commands/compilescss.py
sass_processor/templatetags/__init__.py
sass_processor/templatetags/sass_tags.py
django_sass_processor-1.4.1.dist-info/LICENSE-MIT
django_sass_processor-1.4.1.dist-info/METADATA
django_sass_processor-1.4.1.dist-info/WHEEL
django_sass_processor-1.4.1.dist-info/top_level.txt
django_sass_processor-1.4.1.dist-info/RECORD
