Metadata-Version: 2.1
Name: django-sass-processor
Version: 1.4.1
Summary: SASS processor to compile SCSS files into *.css, while rendering, or offline.
Home-page: https://github.com/jrief/django-sass-processor
Author: Jacob Rief
Author-email: jacob.rief@gmail.com
License: MIT
Keywords: django,sass
Classifier: Development Status :: 5 - Production/Stable
Classifier: Environment :: Web Environment
Classifier: Framework :: Django
Classifier: Intended Audience :: Developers
Classifier: License :: OSI Approved :: MIT License
Classifier: Operating System :: OS Independent
Classifier: Programming Language :: Python
Classifier: Topic :: Internet :: WWW/HTTP :: Dynamic Content
Classifier: Programming Language :: Python :: 3.8
Classifier: Programming Language :: Python :: 3.9
Classifier: Programming Language :: Python :: 3.10
Classifier: Programming Language :: Python :: 3.11
Classifier: Programming Language :: Python :: 3.12
Classifier: Framework :: Django :: 3.2
Classifier: Framework :: Django :: 4.2
Classifier: Framework :: Django :: 5.0
License-File: LICENSE-MIT
Provides-Extra: management-command
Requires-Dist: django-compressor>=2.4; extra == "management-command"
